fala_parlamentar/__init__.py
fala_parlamentar/fala_deputado.py
fala_parlamentar/fala_senador.py
fala_parlamentar-0.1.1.dist-info/LICENSE
fala_parlamentar-0.1.1.dist-info/METADATA
fala_parlamentar-0.1.1.dist-info/WHEEL
fala_parlamentar-0.1.1.dist-info/top_level.txt
fala_parlamentar-0.1.1.dist-info/RECORD
