Metadata-Version: 2.1
Name: fala-parlamentar
Version: 0.1.1
Summary: Módulo para obtenção dos discursos dos parlamentares via webscraping mantendo a url para a publicação do texto
Author-email: Jeferson Alves <contato@jefersonalves.com>
License: The MIT License
Project-URL: homepage, https://github.com/Jefersonalves/fala-parlamentar
Keywords: web-scraping,senado,camara,congresso-nacional
Classifier: Programming Language :: Python :: 3
Classifier: License :: OSI Approved :: MIT License
Classifier: Operating System :: OS Independent
Requires-Python: >=3.6
License-File: LICENSE
Requires-Dist: beautifulsoup4 >=4.6.3
Requires-Dist: pandas >=0.23.4
Requires-Dist: requests >=2.20.0
